dqs/__init__.py
dqs/calibration.py
dqs/kaplan_meier.py
dqs/torch/__init__.py
dqs/torch/distribution.py
dqs/torch/layer.py
dqs/torch/loss.py
dqs-0.1.dist-info/LICENSE
dqs-0.1.dist-info/METADATA
dqs-0.1.dist-info/WHEEL
dqs-0.1.dist-info/top_level.txt
dqs-0.1.dist-info/RECORD
